{
  "siteName": "Epstein Transparency Act",
  "siteDescription": "A factual database tracking developments around the Epstein Files and the Epstein Transparency Act.",
  "heroTitle": "The Epstein Files",
  "heroSubtitle": "Tracking every document release, court filing, and legislative development in the push for full transparency.",
  "heroCta": "Latest News",
  "socialLinks": [],
  "footerText": "This site is dedicated to factual reporting on the Epstein case. All content is based on documented evidence and verified sources."
}
